reditools/__init__.py
reditools/__main__.py
reditools/alignment_file.py
reditools/alignment_manager.py
reditools/analyze.py
reditools/annotate.py
reditools/compiled_position.py
reditools/compiled_reads.py
reditools/fasta_file.py
reditools/file_utils.py
reditools/homopolymerics.py
reditools/index.py
reditools/logger.py
reditools/reditools.py
reditools/region.py
reditools/rtchecks.py
reditools/utils.py
reditools3-3.4.dist-info/licenses/LICENSE
reditools3-3.4.dist-info/METADATA
reditools3-3.4.dist-info/WHEEL
reditools3-3.4.dist-info/top_level.txt
reditools3-3.4.dist-info/RECORD
